[
    {
        "공모전 제목": "TS보안 허점을 찾아라 공모전",
        "분류": "게임/소프트웨어",
        "주최자": "한국교통안전공단",
        "남은 기간": "D-6",
        "접수 기간": "2024-11-15 ~ 2024-11-22",
        "상태": "마감임박"
    },
    {
        "공모전 제목": "[참여비 지급] 일정 관리 서비스 인터뷰 참여자 모집",
        "분류": "게임/소프트웨어",
        "주최자": "주식회사 러너스",
        "남은 기간": "D-1",
        "접수 기간": "2024-11-11 ~ 2024-11-17",
        "상태": "마감임박"
    },
    {
        "공모전 제목": "2024 SBA X 슈퍼빌런랩스 게임 콘테스트(제작 부문) 공모",
        "분류": "게임/소프트웨어, 사진",
        "주최자": "서울특별시,서울경제진흥원(SBA),슈퍼빌런랩스",
        "남은 기간": "D-12",
        "접수 기간": "2024-11-07 ~ 2024-11-28",
        "상태": "접수중"
    },
    {
        "공모전 제목": "제 2회 (주) NovaLoop배 게임 제작 공모전",
        "분류": "게임/소프트웨어",
        "주최자": "(주) NovaLoop",
        "남은 기간": "D-14",
        "접수 기간": "2024-11-01 ~ 2024-11-30",
        "상태": "접수중"
    },
    {
        "공모전 제목": "[공모전, TTS Content Challenge] 숏츠 만들고 총 1,000만원 상당의 경품 받아가세요!",
        "분류": "게임/소프트웨어, 디자인, 사진, 영상/UCC",
        "주최자": "수퍼톤",
        "남은 기간": "D-8",
        "접수 기간": "2024-10-31 ~ 2024-11-24",
        "상태": "접수중"
    },
    {
        "공모전 제목": "2024년 클라우드 아이디어 공모전",
        "분류": "게임/소프트웨어, 기획/아이디어",
        "주최자": "부산광역시",
        "남은 기간": "D-1",
        "접수 기간": "2024-10-14 ~ 2024-11-17",
        "상태": "마감임박"
    },
    {
        "공모전 제목": "SW융합 클러스터 플랫폼 활용 아이디어 경진대회",
        "분류": "게임/소프트웨어, 기획/아이디어",
        "주최자": "한국전자기술연구원",
        "남은 기간": "-",
        "접수 기간": "2024-10-04 ~ 2024-11-10",
        "상태": "마감"
    },
    {
        "공모전 제목": "2024 제5회 크리에이티브 브릿지 페스티벌",
        "분류": "게임/소프트웨어, 디자인, 미술",
        "주최자": "성균관대학교 문화예술미디어융합원",
        "남은 기간": "D-4",
        "접수 기간": "2024-10-21 ~ 2024-11-20",
        "상태": "마감임박"
    },
    {
        "공모전 제목": "헬로소프트 코스페이시스 작품 공모전",
        "분류": "게임/소프트웨어, 기획/아이디어",
        "주최자": "헬로소프트",
        "남은 기간": "D-14",
        "접수 기간": "2024-11-17 ~ 2024-11-30",
        "상태": "접수중"
    },
    {
        "공모전 제목": "디지털 콜럼버스 프로젝트 아이디어 공모전",
        "분류": "게임/소프트웨어, 과학, 기획/아이디어",
        "주최자": "과학기술정보통신부",
        "남은 기간": "-",
        "접수 기간": "2024-10-21 ~ 2024-11-08",
        "상태": "마감"
    },
    {
        "공모전 제목": "AI, ICT의 미래를 그려줘",
        "분류": "게임/소프트웨어, 과학, 기획/아이디어, 디자인",
        "주최자": "과학기술정보통신부",
        "남은 기간": "-",
        "접수 기간": "2024-10-14 ~ 2024-11-08",
        "상태": "마감"
    },
    {
        "공모전 제목": "컴투스 글로벌 게임개발 공모전 ‘컴:온 2024’",
        "분류": "게임/소프트웨어",
        "주최자": "컴투스, 게임문화재단",
        "남은 기간": "D-44",
        "접수 기간": "2024-11-19 ~ 2024-12-30",
        "상태": "접수예정"
    },
    {
        "공모전 제목": "2024~2025년 한국석유공사 데이터 분석 공모전",
        "분류": "게임/소프트웨어, 기획/아이디어",
        "주최자": "한국석유공사",
        "남은 기간": "D-67",
        "접수 기간": "2024-10-14 ~ 2025-01-22",
        "상태": "접수중"
    },
    {
        "공모전 제목": "제 1회 \"비전공자만 지원 가능한\" AI로 홈페이지 제작하기 공모전",
        "분류": "게임/소프트웨어, 기획/아이디어, 디자인",
        "주최자": "코드스프링(Code-spring)",
        "남은 기간": "-",
        "접수 기간": "2024-10-02 ~ 2024-11-15",
        "상태": "마감"
    },
    {
        "공모전 제목": "DreamLink: Beyond Reality '청춘의 크로스로드' 20대 공모전",
        "분류": "게임/소프트웨어",
        "주최자": "럭키플래닛 게임즈",
        "남은 기간": "D-4",
        "접수 기간": "2024-10-16 ~ 2024-11-20",
        "상태": "마감임박"
    },
    {
        "공모전 제목": "게임문화 그림일기 및 광고 포스터 공모전",
        "분류": "게임/소프트웨어, 광고/마케팅, 기획/아이디어, 네이밍/슬로건, 문학/수기, 미술",
        "주최자": "한국게임산업협회, 한국콘텐츠진흥원",
        "남은 기간": "-",
        "접수 기간": "2024-10-11 ~ 2024-10-25",
        "상태": "마감"
    },
    {
        "공모전 제목": "NOVA LOOP 게임 아이디어 공모전 2024",
        "분류": "게임/소프트웨어, 기획/아이디어",
        "주최자": "㈜NovaLoop",
        "남은 기간": "-",
        "접수 기간": "2024-09-19 ~ 2024-10-17",
        "상태": "마감"
    },
    {
        "공모전 제목": "2024 자동차 데이터 분석 경진대회",
        "분류": "게임/소프트웨어",
        "주최자": "산업통상자원부, 한국산업기술진흥원",
        "남은 기간": "-",
        "접수 기간": "2024-10-02 ~ 2024-10-18",
        "상태": "마감"
    },
    {
        "공모전 제목": "제1회 해양기업 디지털전환 우수사례·아이디어 공모전",
        "분류": "게임/소프트웨어, 과학, 기획/아이디어, 대회",
        "주최자": "한국해양진흥공사",
        "남은 기간": "-",
        "접수 기간": "2024-10-07 ~ 2024-10-25",
        "상태": "마감"
    },
    {
        "공모전 제목": "데이터·AI를 활용한 물가 예측 경진대회 : 농산물 가격을 중심으로",
        "분류": "게임/소프트웨어, 대회",
        "주최자": "디지털플랫폼정부위원회, 농림축산식품부",
        "남은 기간": "-",
        "접수 기간": "2024-10-01 ~ 2024-10-14",
        "상태": "마감"
    },
    {
        "공모전 제목": "NC와 함께하는 2024 울산 게임기획 공모전",
        "분류": "게임/소프트웨어",
        "주최자": "울산광역시, 문화체육관광부",
        "남은 기간": "-",
        "접수 기간": "2024-09-11 ~ 2024-10-25",
        "상태": "마감"
    },
    {
        "공모전 제목": "2024 NH 투자증권 빅데이터 경진대회",
        "분류": "게임/소프트웨어, 과학, 대회, 취업/창업",
        "주최자": "NH 투자증권",
        "남은 기간": "-",
        "접수 기간": "2024-08-12 ~ 2024-10-11",
        "상태": "마감"
    },
    {
        "공모전 제목": "﻿제2회 경기도자율주행센터 자율주행 데이터 활용 경진대회",
        "분류": "게임/소프트웨어, 대회",
        "주최자": "경기도자율주행센터",
        "남은 기간": "-",
        "접수 기간": "2024-09-20 ~ 2024-09-30",
        "상태": "마감"
    },
    {
        "공모전 제목": "2024 전국 대학생 SW창업 아이디어톤",
        "분류": "게임/소프트웨어, 취업/창업",
        "주최자": "한양대학교 ERICA SW중심대학사업단",
        "남은 기간": "-",
        "접수 기간": "2024-09-09 ~ 2024-10-27",
        "상태": "마감"
    },
    {
        "공모전 제목": "2024 전국 대학생 SW창업 아이디어톤",
        "분류": "게임/소프트웨어, 기획/아이디어",
        "주최자": "한양대학교",
        "남은 기간": "-",
        "접수 기간": "2024-09-09 ~ 2024-10-27",
        "상태": "마감"
    },
    {
        "공모전 제목": "2024 콘텐츠 변형 탐지 데이터톤 경진대회",
        "분류": "게임/소프트웨어",
        "주최자": "과학기술정보통신부, 정보통신기획평가원",
        "남은 기간": "-",
        "접수 기간": "2024-09-02 ~ 2024-09-30",
        "상태": "마감"
    },
    {
        "공모전 제목": "2024 농어촌 디지털 트윈 서비스 아이디어 경진대회",
        "분류": "게임/소프트웨어, 기획/아이디어, 대회",
        "주최자": "포항공과대학교 산학협력단",
        "남은 기간": "-",
        "접수 기간": "2024-09-12 ~ 2024-10-11",
        "상태": "마감"
    },
    {
        "공모전 제목": "2024 레드브릭 온라인 게임 잼",
        "분류": "게임/소프트웨어",
        "주최자": "레드브릭",
        "남은 기간": "-",
        "접수 기간": "2024-09-11 ~ 2024-10-20",
        "상태": "마감"
    },
    {
        "공모전 제목": "2024 제 24회 대학생 프로그래밍 경시대회",
        "분류": "게임/소프트웨어, 과학",
        "주최자": "한국지능정보사회진흥원",
        "남은 기간": "-",
        "접수 기간": "2024-09-13 ~ 2024-09-27",
        "상태": "마감"
    },
    {
        "공모전 제목": "제 12회 2024 빅콘테스트",
        "분류": "게임/소프트웨어, 기획/아이디어, 대회",
        "주최자": "한국정보통신진흥협회",
        "남은 기간": "-",
        "접수 기간": "2024-09-09 ~ 2024-10-25",
        "상태": "마감"
    },
    {
        "공모전 제목": "제16회 소외된 이웃과 함께하는 창의설계 경진대회",
        "분류": "게임/소프트웨어, 과학, 기획/아이디어, 디자인",
        "주최자": "대전·세종·충남 지역혁신플랫폼, 사단법인 나눔과기술, 국립중앙과학관, 공생",
        "남은 기간": "-",
        "접수 기간": "2024-09-01 ~ 2024-10-04",
        "상태": "마감"
    },
    {
        "공모전 제목": "2024 제13회 SW개발 공모전 : 피우다 프로젝트(환경 문제 해결)",
        "분류": "게임/소프트웨어, 기획/아이디어, 대회",
        "주최자": "과학기술정보통신부",
        "남은 기간": "-",
        "접수 기간": "2024-09-04 ~ 2024-10-06",
        "상태": "마감"
    },
    {
        "공모전 제목": "분당서울대학교병원 급성신손상 환자 데이터톤",
        "분류": "게임/소프트웨어, 기획/아이디어",
        "주최자": "주식회사 에이아이네이션",
        "남은 기간": "-",
        "접수 기간": "2024-08-25 ~ 2024-09-10",
        "상태": "마감"
    },
    {
        "공모전 제목": "2024 대한민국 소프트웨어 기술대상 및 IT아키텍처상",
        "분류": "게임/소프트웨어",
        "주최자": "(사)한국소프트웨어기술진흥협회",
        "남은 기간": "-",
        "접수 기간": "2024-09-09 ~ 2024-09-27",
        "상태": "마감"
    },
    {
        "공모전 제목": "2024년 홍천군 공공데이터 활용·분석 공모전",
        "분류": "게임/소프트웨어, 기획/아이디어, 취업/창업",
        "주최자": "홍천군청",
        "남은 기간": "-",
        "접수 기간": "2024-09-02 ~ 2024-09-27",
        "상태": "마감"
    },
    {
        "공모전 제목": "2024 실험실 팀빌딩 해커톤 경진대회",
        "분류": "게임/소프트웨어, 대회",
        "주최자": "인하대학교 창업지원단",
        "남은 기간": "-",
        "접수 기간": "2024-08-30 ~ 2024-09-13",
        "상태": "마감"
    },
    {
        "공모전 제목": "[부천국제애니메이션페스티벌] BIAF2024 단편애니메이션제작지원 공모",
        "분류": "게임/소프트웨어, 기획/아이디어, 만화/캐릭터, 영상/UCC, 취업/창업",
        "주최자": "부천국제애니메이션 페스티벌조직위원회",
        "남은 기간": "-",
        "접수 기간": "2024-08-01 ~ 2024-09-23",
        "상태": "마감"
    },
    {
        "공모전 제목": "[부천국제애니메이션페스티벌] BIAF2024 애니프리젠테이션 공모",
        "분류": "게임/소프트웨어, 기획/아이디어, 디자인, 만화/캐릭터, 문학/수기, 미술, 영상/UCC, 취업/창업",
        "주최자": "부천국제애니메이션 페스티벌조직위원회",
        "남은 기간": "-",
        "접수 기간": "2024-08-01 ~ 2024-09-23",
        "상태": "마감"
    },
    {
        "공모전 제목": "WEB2X Ideaton ‘connecTHON’",
        "분류": "게임/소프트웨어, 광고/마케팅, 기획/아이디어",
        "주최자": "(주)씨피랩스",
        "남은 기간": "-",
        "접수 기간": "2024-09-02 ~ 2024-09-22",
        "상태": "마감"
    },
    {
        "공모전 제목": "헥사월드 방꾸미기 콘테스트 : 꾸미기 기능을 활용하여 자신의 방을 꾸며주세요!",
        "분류": "게임/소프트웨어, 디자인, 이벤트",
        "주최자": "데이터킹(주)",
        "남은 기간": "-",
        "접수 기간": "2024-08-29 ~ 2024-09-30",
        "상태": "마감"
    },
    {
        "공모전 제목": "2024 제1회 국방 AI 아이디어톤",
        "분류": "게임/소프트웨어, 대회",
        "주최자": "국방부, 정보통신기획평가원",
        "남은 기간": "-",
        "접수 기간": "2024-08-08 ~ 2024-10-07",
        "상태": "마감"
    },
    {
        "공모전 제목": "2024 부산 체험관광 콘텐츠 공모전",
        "분류": "게임/소프트웨어, 광고/마케팅, 기획/아이디어, 디자인, 영상/UCC",
        "주최자": "부산관광공사",
        "남은 기간": "-",
        "접수 기간": "2024-08-12 ~ 2024-09-09",
        "상태": "마감"
    },
    {
        "공모전 제목": "2024 이지랩 메이커톤",
        "분류": "게임/소프트웨어, 기획/아이디어, 디자인, 취업/창업",
        "주최자": "동국대 메이커스페이스 이지랩",
        "남은 기간": "-",
        "접수 기간": "2024-08-21 ~ 2024-08-29",
        "상태": "마감"
    },
    {
        "공모전 제목": "충청권 인디게임 공모전 [인디유]",
        "분류": "게임/소프트웨어",
        "주최자": "충남정보문화산업진흥원, 대전정보문화산업진흥원, 청주시문화산업진흥재단",
        "남은 기간": "-",
        "접수 기간": "2024-08-19 ~ 2024-09-20",
        "상태": "마감"
    },
    {
        "공모전 제목": "2024 NH투자증권 빅데이터 경진대회 (~10/11)",
        "분류": "게임/소프트웨어, 대회",
        "주최자": "NH투자증권",
        "남은 기간": "-",
        "접수 기간": "2024-08-12 ~ 2024-10-11",
        "상태": "마감"
    },
    {
        "공모전 제목": "충청남도 데이터 분석 아이디어 공모전",
        "분류": "게임/소프트웨어, 기획/아이디어",
        "주최자": "충청남도",
        "남은 기간": "-",
        "접수 기간": "2024-08-01 ~ 2024-08-30",
        "상태": "마감"
    },
    {
        "공모전 제목": "﻿2024 광주 청년주간 청년 AI그림대회",
        "분류": "게임/소프트웨어, 대회, 미술",
        "주최자": "광주광역시",
        "남은 기간": "-",
        "접수 기간": "2024-08-16 ~ 2024-09-06",
        "상태": "마감"
    },
    {
        "공모전 제목": "[2024 재외동포 통일문화 행사] AI 통일 아트 챌린지",
        "분류": "게임/소프트웨어, 미술, 해외",
        "주최자": "통일부",
        "남은 기간": "-",
        "접수 기간": "2024-08-19 ~ 2024-09-06",
        "상태": "마감"
    },
    {
        "공모전 제목": "2024 경기 메타버스 아이디어톤",
        "분류": "게임/소프트웨어, 광고/마케팅, 기획/아이디어",
        "주최자": "과학기술정보통신부, 경기도",
        "남은 기간": "-",
        "접수 기간": "2024-08-16 ~ 2024-09-01",
        "상태": "마감"
    },
    {
        "공모전 제목": "제8회 디지털 헬스케어 MEDICAL HACK 2024 공고",
        "분류": "게임/소프트웨어, 과학, 기획/아이디어, 취업/창업",
        "주최자": "부산광역시, 부산테크노파크, 부산대학교, 부산대학교병원",
        "남은 기간": "-",
        "접수 기간": "2024-08-08 ~ 2024-09-30",
        "상태": "마감"
    },
    {
        "공모전 제목": "[2024년 지역주도 디지털혁신지원사업] 제11회 전국 ICT융합 공모전",
        "분류": "게임/소프트웨어, 기획/아이디어",
        "주최자": "과학기술정보통신부, 충청북도",
        "남은 기간": "-",
        "접수 기간": "2024-08-01 ~ 2024-10-31",
        "상태": "마감"
    },
    {
        "공모전 제목": "DIVE 2024(글로벌 데이터 해커톤 대회)",
        "분류": "게임/소프트웨어, 과학, 기획/아이디어, 대회",
        "주최자": "부산광역시",
        "남은 기간": "-",
        "접수 기간": "2024-08-13 ~ 2024-09-03",
        "상태": "마감"
    },
    {
        "공모전 제목": "남해 미션투어 콘테스트",
        "분류": "게임/소프트웨어, 기획/아이디어, 디자인",
        "주최자": "남해군관광문화재단",
        "남은 기간": "-",
        "접수 기간": "2024-08-09 ~ 2024-08-20",
        "상태": "마감"
    },
    {
        "공모전 제목": "LEMONATION 리듬게임 ⟪KALPA⟫ GAME MUSIC 레모네이션",
        "분류": "게임/소프트웨어, 음악",
        "주최자": "레몬사운드",
        "남은 기간": "-",
        "접수 기간": "2024-08-07 ~ 2024-10-02",
        "상태": "마감"
    },
    {
        "공모전 제목": "생성형 AI를 활용한 TIMT 캐릭터 제작",
        "분류": "게임/소프트웨어, 기획/아이디어, 디자인",
        "주최자": "MAKE8",
        "남은 기간": "-",
        "접수 기간": "2024-08-12 ~ 2024-09-01",
        "상태": "마감"
    },
    {
        "공모전 제목": "2024 항만혁신 국민제안 공모",
        "분류": "게임/소프트웨어, 기획/아이디어",
        "주최자": "부산항만공사",
        "남은 기간": "-",
        "접수 기간": "2024-08-05 ~ 2024-09-01",
        "상태": "마감"
    },
    {
        "공모전 제목": "제2회 신약개발 AI 경진대회",
        "분류": "게임/소프트웨어, 기획/아이디어",
        "주최자": "한국제약바이오협회 AI신약융합연구원",
        "남은 기간": "-",
        "접수 기간": "2024-08-05 ~ 2024-09-23",
        "상태": "마감"
    },
    {
        "공모전 제목": "FSI AIxData Challenge 2024",
        "분류": "게임/소프트웨어",
        "주최자": "금융보안원",
        "남은 기간": "-",
        "접수 기간": "2024-08-05 ~ 2024-08-30",
        "상태": "마감"
    },
    {
        "공모전 제목": "2024 전북 인디게임 공모전",
        "분류": "게임/소프트웨어, 기획/아이디어",
        "주최자": "전북특별자치도, 한국콘텐츠진흥원, 전북특별자치도 콘텐츠융합진흥원",
        "남은 기간": "-",
        "접수 기간": "2024-08-05 ~ 2024-09-13",
        "상태": "마감"
    },
    {
        "공모전 제목": "대한민국AI국제영화제",
        "분류": "게임/소프트웨어, 기획/아이디어, 영상/UCC",
        "주최자": "경기도",
        "남은 기간": "-",
        "접수 기간": "2024-08-01 ~ 2024-09-06",
        "상태": "마감"
    },
    {
        "공모전 제목": "2024 데이터 크리에이터 캠프",
        "분류": "게임/소프트웨어, 과학, 대회, 영상/UCC",
        "주최자": "과학기술정보통신부",
        "남은 기간": "-",
        "접수 기간": "2024-08-05 ~ 2024-09-10",
        "상태": "마감"
    },
    {
        "공모전 제목": "2024 제2회 KISIA 정보보호 개발자 해커톤",
        "분류": "게임/소프트웨어, 대회",
        "주최자": "과학기술정보통신부",
        "남은 기간": "-",
        "접수 기간": "2024-07-01 ~ 2024-08-04",
        "상태": "마감"
    },
    {
        "공모전 제목": "2024 WASD 인디게임 공모전",
        "분류": "게임/소프트웨어",
        "주최자": "스토브인디",
        "남은 기간": "-",
        "접수 기간": "2024-07-31 ~ 2024-08-20",
        "상태": "마감"
    },
    {
        "공모전 제목": "2024 로봇공감 로.그.인(로봇 그리고 인간) 로봇사진 공모전",
        "분류": "게임/소프트웨어, 과학, 사진",
        "주최자": "(주)로봇신문사",
        "남은 기간": "-",
        "접수 기간": "2024-07-17 ~ 2024-08-31",
        "상태": "마감"
    },
    {
        "공모전 제목": "2024 AI 헬스케어 아이디어톤 경진대회",
        "분류": "게임/소프트웨어, 과학, 기획/아이디어",
        "주최자": "강원지역혁신플랫폼 데이터혁신본부",
        "남은 기간": "-",
        "접수 기간": "2024-07-29 ~ 2024-08-11",
        "상태": "마감"
    },
    {
        "공모전 제목": "2024년 강릉시 데이터분석 공모전(연장)",
        "분류": "게임/소프트웨어, 기획/아이디어, 대회",
        "주최자": "강릉시청",
        "남은 기간": "-",
        "접수 기간": "2024-07-26 ~ 2024-10-01",
        "상태": "마감"
    },
    {
        "공모전 제목": "2024 사이버시큐리티 해커톤 대회",
        "분류": "게임/소프트웨어, 과학, 기획/아이디어, 대회",
        "주최자": "과학기술정보통신부",
        "남은 기간": "-",
        "접수 기간": "2024-07-24 ~ 2024-08-30",
        "상태": "마감"
    },
    {
        "공모전 제목": "민관협력 지원 플랫폼 활용 디지털 사회혁신 서비스 개발·아이디어 공모전",
        "분류": "게임/소프트웨어, 과학, 기획/아이디어",
        "주최자": "과학기술정보통신부",
        "남은 기간": "-",
        "접수 기간": "2024-07-25 ~ 2024-09-10",
        "상태": "마감"
    },
    {
        "공모전 제목": "제10회 과학치안 아이디어 공모전",
        "분류": "게임/소프트웨어, 과학, 기획/아이디어",
        "주최자": "과학기술정보통신부, 경찰청",
        "남은 기간": "-",
        "접수 기간": "2024-07-22 ~ 2024-08-29",
        "상태": "마감"
    },
    {
        "공모전 제목": "2024 충청권 ICT 이노베이션 아이디어 및 SW개발 공모전",
        "분류": "게임/소프트웨어, 기획/아이디어",
        "주최자": "과학기술정보통신부, 정보통신산업진흥원",
        "남은 기간": "-",
        "접수 기간": "2024-07-22 ~ 2024-08-30",
        "상태": "마감"
    },
    {
        "공모전 제목": "제24회 모바일 기술대상(The 24nd Mobile Technology Awards)",
        "분류": "게임/소프트웨어, 과학, 기획/아이디어",
        "주최자": "과학기술정보통신부",
        "남은 기간": "-",
        "접수 기간": "2024-07-08 ~ 2024-08-14",
        "상태": "마감"
    },
    {
        "공모전 제목": "작전명 : 임팩트타운 - 살고 싶은 세계 만들기",
        "분류": "게임/소프트웨어, 기획/아이디어",
        "주최자": "임팩트닷커리어",
        "남은 기간": "-",
        "접수 기간": "2024-07-19 ~ 2024-08-01",
        "상태": "마감"
    },
    {
        "공모전 제목": "제2회 전북청년 빅데이터 경진대회",
        "분류": "게임/소프트웨어, 대회",
        "주최자": "전북 빅데이터 기술교류 공동연구회, 우석대학교, 전북대학교 빅데이터 혁신융합대학 사업단",
        "남은 기간": "-",
        "접수 기간": "2024-06-17 ~ 2024-08-30",
        "상태": "마감"
    },
    {
        "공모전 제목": "2024 서울 AI스토리공모전 <테크놀서울>",
        "분류": "게임/소프트웨어, 과학, 문학/수기",
        "주최자": "서울특별시",
        "남은 기간": "-",
        "접수 기간": "2024-07-16 ~ 2024-08-15",
        "상태": "마감"
    },
    {
        "공모전 제목": "2024년 자율주행 인공지능 알고리즘 개발 챌린지",
        "분류": "게임/소프트웨어, 과학, 취업/창업",
        "주최자": "엠데이터싱크",
        "남은 기간": "-",
        "접수 기간": "2024-07-15 ~ 2024-07-26",
        "상태": "마감"
    },
    {
        "공모전 제목": "2024 인디(inD) 게임잼 대전",
        "분류": "게임/소프트웨어, 기획/아이디어, 디자인",
        "주최자": "대전정보문화산업진흥원, 대전글로벌게임센터, 목원대학교, 대전게임·콘텐츠협회",
        "남은 기간": "-",
        "접수 기간": "2024-07-18 ~ 2024-07-25",
        "상태": "마감"
    },
    {
        "공모전 제목": "제임스 다이슨 어워드 2024",
        "분류": "게임/소프트웨어, 기획/아이디어, 디자인",
        "주최자": "제임스 다이슨 재단",
        "남은 기간": "-",
        "접수 기간": "2024-04-01 ~ 2024-07-17",
        "상태": "마감"
    },
    {
        "공모전 제목": "제11회 대한민국 SW융합 해커톤 대회",
        "분류": "게임/소프트웨어",
        "주최자": "과학기술정보통신부",
        "남은 기간": "-",
        "접수 기간": "2024-06-21 ~ 2024-07-26",
        "상태": "마감"
    },
    {
        "공모전 제목": "2024년 제11회 소프트웨어 개발보안 경진대회",
        "분류": "게임/소프트웨어",
        "주최자": "과학기술정보통신부",
        "남은 기간": "-",
        "접수 기간": "2024-07-02 ~ 2024-08-02",
        "상태": "마감"
    },
    {
        "공모전 제목": "2024년 제11회 소프트웨어 개발보안 경진대회 개최",
        "분류": "게임/소프트웨어",
        "주최자": "한국인터넷진흥원",
        "남은 기간": "-",
        "접수 기간": "2024-07-02 ~ 2024-08-02",
        "상태": "마감"
    },
    {
        "공모전 제목": "2024 리얼루전 글로벌 3D 캐릭터 공모전",
        "분류": "게임/소프트웨어, 디자인, 만화/캐릭터",
        "주최자": "Reallusion",
        "남은 기간": "-",
        "접수 기간": "2024-05-15 ~ 2024-09-01",
        "상태": "마감"
    },
    {
        "공모전 제목": "2024 스마트농업 AI 경진대회",
        "분류": "게임/소프트웨어, 과학, 기획/아이디어, 대회",
        "주최자": "농림축산식품부",
        "남은 기간": "-",
        "접수 기간": "2024-07-02 ~ 2024-07-26",
        "상태": "마감"
    },
    {
        "공모전 제목": "2024 제2회 포톤 게임잼",
        "분류": "게임/소프트웨어, 기획/아이디어",
        "주최자": "(주)웰데이타시스템",
        "남은 기간": "-",
        "접수 기간": "2024-06-24 ~ 2024-07-21",
        "상태": "마감"
    },
    {
        "공모전 제목": "﻿2024년 게임인재단 공모전 - AI를 활용한 한국의 문화·역사 창작 콘텐츠",
        "분류": "게임/소프트웨어, 기획/아이디어",
        "주최자": "게임인재단",
        "남은 기간": "-",
        "접수 기간": "2024-07-01 ~ 2024-07-31",
        "상태": "마감"
    },
    {
        "공모전 제목": "2024 자율성장 인공지능 경진대회 'Fashion-How season5'",
        "분류": "게임/소프트웨어, 과학, 대회",
        "주최자": "한국전자통신연구원(ETRI)",
        "남은 기간": "-",
        "접수 기간": "2024-06-26 ~ 2024-07-26",
        "상태": "마감"
    },
    {
        "공모전 제목": "﻿2024 디스플레이 챌린지 (DISPLAY CHALLENGE) 공모전",
        "분류": "게임/소프트웨어, 과학, 기획/아이디어, 대회, 디자인, 취업/창업",
        "주최자": "산업통상자원부",
        "남은 기간": "-",
        "접수 기간": "2024-06-26 ~ 2024-07-26",
        "상태": "마감"
    },
    {
        "공모전 제목": "2024 충청권 대학(원)생 사이버위협 시나리오 공모전",
        "분류": "게임/소프트웨어, 과학",
        "주최자": "대전광역시, 충남대학교 융합보안연구센터 등",
        "남은 기간": "-",
        "접수 기간": "2024-06-24 ~ 2024-09-10",
        "상태": "마감"
    },
    {
        "공모전 제목": "자율협력주행·C-ITS 기반 모빌리티 기술 및 서비스 지원 공모전",
        "분류": "게임/소프트웨어, 과학",
        "주최자": "국토교통부",
        "남은 기간": "-",
        "접수 기간": "2024-06-17 ~ 2024-07-16",
        "상태": "마감"
    },
    {
        "공모전 제목": "﻿2024년 관광지식정보시스템 관광데이터 분석 공모전",
        "분류": "게임/소프트웨어, 논문",
        "주최자": "한국문화관광연구원",
        "남은 기간": "-",
        "접수 기간": "2024-06-17 ~ 2024-07-15",
        "상태": "마감"
    },
    {
        "공모전 제목": "2024 도서관 데이터 활용 공모전",
        "분류": "게임/소프트웨어, 광고/마케팅, 기획/아이디어, 디자인, 영상/UCC",
        "주최자": "국립중앙도서관",
        "남은 기간": "-",
        "접수 기간": "2024-06-17 ~ 2024-08-30",
        "상태": "마감"
    },
    {
        "공모전 제목": "제2회 개인정보보호 모의재판 경연대회",
        "분류": "게임/소프트웨어, 과학, 논문, 대회, 취업/창업",
        "주최자": "개인정보보호위원회",
        "남은 기간": "-",
        "접수 기간": "2024-06-12 ~ 2024-07-17",
        "상태": "마감"
    },
    {
        "공모전 제목": "2024 현대모비스 알고리즘 경진대회",
        "분류": "게임/소프트웨어, 기획/아이디어",
        "주최자": "현대모비스",
        "남은 기간": "-",
        "접수 기간": "2024-05-29 ~ 2024-06-25",
        "상태": "마감"
    },
    {
        "공모전 제목": "2024 외교 공공데이터 활용 경진대회 개최",
        "분류": "게임/소프트웨어, 기획/아이디어, 대회, 해외",
        "주최자": "외교부",
        "남은 기간": "-",
        "접수 기간": "2024-05-16 ~ 2024-07-15",
        "상태": "마감"
    },
    {
        "공모전 제목": "제 4회 KOPIS 빅데이터 공모전",
        "분류": "게임/소프트웨어, 기획/아이디어",
        "주최자": "예술경영지원센터",
        "남은 기간": "-",
        "접수 기간": "2024-06-10 ~ 2024-07-11",
        "상태": "마감"
    },
    {
        "공모전 제목": "2024년 전국 대학생 디지털콘텐츠 기획 공모전",
        "분류": "게임/소프트웨어, 광고/마케팅, 기획/아이디어, 영상/UCC",
        "주최자": "한국SNS마케팅진흥원",
        "남은 기간": "-",
        "접수 기간": "2024-06-15 ~ 2024-06-30",
        "상태": "마감"
    },
    {
        "공모전 제목": "상상은 크게, 개발은 빠르게! 로우코드 앱 개발 공모전",
        "분류": "게임/소프트웨어, 기획/아이디어",
        "주최자": "영림원소프트랩, 플렉스튜디오, ZDnet",
        "남은 기간": "-",
        "접수 기간": "2024-06-10 ~ 2024-09-20",
        "상태": "마감"
    },
    {
        "공모전 제목": "2024 MYME GAMEJAM 참가자 모집",
        "분류": "게임/소프트웨어",
        "주최자": "주식회사 공감오래콘텐츠, 마이미글로벌센터",
        "남은 기간": "-",
        "접수 기간": "2024-06-03 ~ 2024-06-21",
        "상태": "마감"
    },
    {
        "공모전 제목": "제10회 삼성전자 대학생 프로그래밍 경진대회(SCPC 2024)",
        "분류": "게임/소프트웨어",
        "주최자": "삼성리서치",
        "남은 기간": "-",
        "접수 기간": "2024-06-04 ~ 2024-07-04",
        "상태": "마감"
    },
    {
        "공모전 제목": "미래융합인재 발굴 소프트웨어 챌린지",
        "분류": "게임/소프트웨어, 기획/아이디어",
        "주최자": "경산이노베이션아카데미",
        "남은 기간": "-",
        "접수 기간": "2024-06-03 ~ 2024-06-23",
        "상태": "마감"
    },
    {
        "공모전 제목": "제6회 대구 빅데이터 분석 경진대회",
        "분류": "게임/소프트웨어",
        "주최자": "대구광역시",
        "남은 기간": "-",
        "접수 기간": "2024-06-03 ~ 2024-07-07",
        "상태": "마감"
    },
    {
        "공모전 제목": "2024년 공무원연금공단 공공데이터 활용 대국민 아이디어 공모전(기간연장)",
        "분류": "게임/소프트웨어, 기획/아이디어",
        "주최자": "공무원연금공단",
        "남은 기간": "-",
        "접수 기간": "2024-06-01 ~ 2024-06-14",
        "상태": "마감"
    },
    {
        "공모전 제목": "코드게이트 글로벌 AI 아이디어랩 공모전",
        "분류": "게임/소프트웨어, 기획/아이디어",
        "주최자": "사단법인코드게이트보안포럼, 금융보안원",
        "남은 기간": "-",
        "접수 기간": "2024-04-29 ~ 2024-06-30",
        "상태": "마감"
    },
    {
        "공모전 제목": "2024 TikTok 대학생 AR 필터 메이커톤",
        "분류": "게임/소프트웨어",
        "주최자": "TikTok, (사)한국디지털콘텐츠학회",
        "남은 기간": "-",
        "접수 기간": "2024-05-27 ~ 2024-06-23",
        "상태": "마감"
    },
    {
        "공모전 제목": "제5회 디지털 신기술 아이디어 경진대회",
        "분류": "게임/소프트웨어, 과학, 기획/아이디어, 대회, 취업/창업",
        "주최자": "정보통신산업진흥원",
        "남은 기간": "-",
        "접수 기간": "2024-05-08 ~ 2024-06-11",
        "상태": "마감"
    },
    {
        "공모전 제목": "2024년 공개SW 개발자대회",
        "분류": "게임/소프트웨어, 과학, 기획/아이디어, 대회",
        "주최자": "과학기술정보통신부",
        "남은 기간": "-",
        "접수 기간": "2024-05-29 ~ 2024-07-04",
        "상태": "마감"
    },
    {
        "공모전 제목": "2024 ‘상상 블루 파빌리온’ 아이디어 공모",
        "분류": "게임/소프트웨어, 기획/아이디어",
        "주최자": "KT&G",
        "남은 기간": "-",
        "접수 기간": "2024-05-20 ~ 2024-07-05",
        "상태": "마감"
    },
    {
        "공모전 제목": "[과학기술정보통신부] 2024 메타버스 개발자 경진대회: 위에이알 지정과제",
        "분류": "게임/소프트웨어, 과학",
        "주최자": "과학기술정보통신부",
        "남은 기간": "-",
        "접수 기간": "2024-05-07 ~ 2024-06-07",
        "상태": "마감"
    },
    {
        "공모전 제목": "2024 Epson Innovation Challenge in Korea",
        "분류": "게임/소프트웨어",
        "주최자": "LIKELION",
        "남은 기간": "-",
        "접수 기간": "2024-04-29 ~ 2024-05-26",
        "상태": "마감"
    },
    {
        "공모전 제목": "부산인디커넥트페스티벌2024 인디게임 전시작 접수",
        "분류": "게임/소프트웨어",
        "주최자": "사단법인 부산인디커넥트페스티벌 조직위원회",
        "남은 기간": "-",
        "접수 기간": "2024-04-10 ~ 2024-06-19",
        "상태": "마감"
    },
    {
        "공모전 제목": "2024년 메타버스 개발자 경진대회 참가팀 모집",
        "분류": "게임/소프트웨어, 대회",
        "주최자": "과학기술정보통신부",
        "남은 기간": "-",
        "접수 기간": "2024-05-07 ~ 2024-06-07",
        "상태": "마감"
    },
    {
        "공모전 제목": "2024년 금산군 데이터기반행정 시각화 아이디어 공모전",
        "분류": "게임/소프트웨어, 기획/아이디어",
        "주최자": "금산군",
        "남은 기간": "-",
        "접수 기간": "2024-05-07 ~ 2024-06-30",
        "상태": "마감"
    },
    {
        "공모전 제목": "제 19회 경기게임오디션 청중평가단 모집",
        "분류": "게임/소프트웨어",
        "주최자": "경기콘텐츠진흥원",
        "남은 기간": "-",
        "접수 기간": "2024-05-02 ~ 2024-05-14",
        "상태": "마감"
    },
    {
        "공모전 제목": "콘텐츠 창의인재동반사업 우수 프로젝트 사업화지원 - 게임분야",
        "분류": "게임/소프트웨어, 취업/창업",
        "주최자": "주식회사 젬블로컴퍼니",
        "남은 기간": "-",
        "접수 기간": "2024-04-30 ~ 2024-05-13",
        "상태": "마감"
    },
    {
        "공모전 제목": "제12회 산업통상자원부 공공데이터 활용 아이디어 공모전",
        "분류": "게임/소프트웨어, 기획/아이디어",
        "주최자": "산업통상자원부",
        "남은 기간": "-",
        "접수 기간": "2024-04-30 ~ 2024-07-01",
        "상태": "마감"
    },
    {
        "공모전 제목": "2024 MATLAB 대학생 AI 경진대회",
        "분류": "게임/소프트웨어",
        "주최자": "매스웍스코리아",
        "남은 기간": "-",
        "접수 기간": "2024-04-25 ~ 2024-06-20",
        "상태": "마감"
    },
    {
        "공모전 제목": "HP OMEN 필터 속 국가권력급 HP를 찾아라!",
        "분류": "게임/소프트웨어, 영상/UCC, 이벤트",
        "주최자": "HP Korea",
        "남은 기간": "-",
        "접수 기간": "2024-04-25 ~ 2024-04-30",
        "상태": "마감"
    },
    {
        "공모전 제목": "2024년 차세대 ICT여성리더 육성-협업 프로젝트 지원 사업",
        "분류": "게임/소프트웨어, 취업/창업",
        "주최자": "(사)IT여성기업인협회",
        "남은 기간": "-",
        "접수 기간": "2024-04-26 ~ 2024-05-03",
        "상태": "마감"
    },
    {
        "공모전 제목": "2024년 국방 공공데이터 활용 경진대회",
        "분류": "게임/소프트웨어, 기획/아이디어",
        "주최자": "국방부·병무청·방위사업청",
        "남은 기간": "-",
        "접수 기간": "2024-04-22 ~ 2024-06-10",
        "상태": "마감"
    },
    {
        "공모전 제목": "세상에 없는 '게임책' 공모전",
        "분류": "게임/소프트웨어, 문학/수기",
        "주최자": "길벗 캠퍼스, 글로벌게임연구회",
        "남은 기간": "-",
        "접수 기간": "2024-04-19 ~ 2024-08-31",
        "상태": "마감"
    },
    {
        "공모전 제목": "스파르타코딩클럽X크래프톤 정글 ‘All-in 코딩 공모전: 대학 생활 개선 편’",
        "분류": "게임/소프트웨어, 기획/아이디어",
        "주최자": "팀스파르타",
        "남은 기간": "-",
        "접수 기간": "2024-03-25 ~ 2024-04-28",
        "상태": "마감"
    },
    {
        "공모전 제목": "[데이콘] 저해상도 조류 이미지 분류 AI 경진대회",
        "분류": "게임/소프트웨어, 기획/아이디어",
        "주최자": "데이콘",
        "남은 기간": "-",
        "접수 기간": "2024-04-08 ~ 2024-05-06",
        "상태": "마감"
    },
    {
        "공모전 제목": "2024 공군 창의·혁신 아이디어 공모 해커톤",
        "분류": "게임/소프트웨어, 대회",
        "주최자": "공군본부",
        "남은 기간": "-",
        "접수 기간": "2024-06-01 ~ 2024-07-13",
        "상태": "마감"
    },
    {
        "공모전 제목": "[Blaybus UXUI직무 실전과제] UX/UI 케이스스터디 공모전",
        "분류": "게임/소프트웨어",
        "주최자": "주식회사 블레이버스",
        "남은 기간": "-",
        "접수 기간": "2024-04-15 ~ 2024-05-07",
        "상태": "마감"
    },
    {
        "공모전 제목": "2024년 경상남도 공공데이터 활용 창업경진대회",
        "분류": "게임/소프트웨어, 대회",
        "주최자": "경상남도",
        "남은 기간": "-",
        "접수 기간": "2024-04-01 ~ 2024-06-21",
        "상태": "마감"
    },
    {
        "공모전 제목": "2024 현대오토에버 배리어프리 앱개발 콘테스트",
        "분류": "게임/소프트웨어",
        "주최자": "현대오토에버, 서울사회복지공동모금회",
        "남은 기간": "-",
        "접수 기간": "2024-04-15 ~ 2024-05-19",
        "상태": "마감"
    },
    {
        "공모전 제목": "제10회 2024년 보건의료빅데이터 활용 창업경진대회",
        "분류": "게임/소프트웨어, 기획/아이디어, 대회, 취업/창업",
        "주최자": "보건복지부",
        "남은 기간": "-",
        "접수 기간": "2024-04-08 ~ 2024-05-31",
        "상태": "마감"
    },
    {
        "공모전 제목": "2024년 장애인 분야 해커톤 대회 (장애 플러스 기술)",
        "분류": "게임/소프트웨어, 과학, 기획/아이디어, 대회",
        "주최자": "한국장애인재단",
        "남은 기간": "-",
        "접수 기간": "2024-04-08 ~ 2024-05-08",
        "상태": "마감"
    },
    {
        "공모전 제목": "2024 충청북도 생성형 인공지능 전국 경진대회",
        "분류": "게임/소프트웨어, 과학, 대회",
        "주최자": "충청북도",
        "남은 기간": "-",
        "접수 기간": "2024-04-05 ~ 2024-04-24",
        "상태": "마감"
    },
    {
        "공모전 제목": "2024 관광데이터 활용 공모전",
        "분류": "게임/소프트웨어",
        "주최자": "한국관광공사, 카카오",
        "남은 기간": "-",
        "접수 기간": "2024-04-03 ~ 2024-05-09",
        "상태": "마감"
    },
    {
        "공모전 제목": "2024년 충청북도 공공데이터 활용 창업경진대회",
        "분류": "게임/소프트웨어, 기획/아이디어",
        "주최자": "충청북도",
        "남은 기간": "-",
        "접수 기간": "2024-03-25 ~ 2024-05-24",
        "상태": "마감"
    },
    {
        "공모전 제목": "2024 인디크래프트",
        "분류": "게임/소프트웨어",
        "주최자": "성남시,성남산업진흥원,한국모바일게임협회",
        "남은 기간": "-",
        "접수 기간": "2024-03-29 ~ 2024-04-22",
        "상태": "마감"
    },
    {
        "공모전 제목": "7TH  BNW MOS 월드챔피언쉽 국가대표 선발 경진대회",
        "분류": "게임/소프트웨어, 대회",
        "주최자": "YBM",
        "남은 기간": "-",
        "접수 기간": "2024-03-25 ~ 2024-04-28",
        "상태": "마감"
    },
    {
        "공모전 제목": "붕어빵 유니버스 공모전",
        "분류": "게임/소프트웨어, 디자인",
        "주최자": "컴투스플랫폼",
        "남은 기간": "-",
        "접수 기간": "2024-03-15 ~ 2024-04-15",
        "상태": "마감"
    },
    {
        "공모전 제목": "제 19회 경기게임오디션",
        "분류": "게임/소프트웨어",
        "주최자": "경기콘텐츠진흥원",
        "남은 기간": "-",
        "접수 기간": "2024-03-15 ~ 2024-04-15",
        "상태": "마감"
    },
    {
        "공모전 제목": "제1회 ASUS ROG X GeForce 노트북 생성형 AI 이미지 공모전",
        "분류": "게임/소프트웨어",
        "주최자": "ASUS KOREA",
        "남은 기간": "-",
        "접수 기간": "2024-03-11 ~ 2024-04-09",
        "상태": "마감"
    },
    {
        "공모전 제목": "2024년 영주시 데이터 분석·활용 공모전",
        "분류": "게임/소프트웨어, 기획/아이디어",
        "주최자": "영주시청",
        "남은 기간": "-",
        "접수 기간": "2024-03-01 ~ 2024-04-30",
        "상태": "마감"
    },
    {
        "공모전 제목": "2024 퐁당청양 사회적경제 창업경진대회",
        "분류": "건축, 게임/소프트웨어, 과학, 광고/마케팅, 기획/아이디어, 대회, 디자인, 문학/수기, 미술, 사진, 영상/UCC, 음악, 이벤트, 취업/창업",
        "주최자": "청양군",
        "남은 기간": "-",
        "접수 기간": "2024-02-28 ~ 2024-03-28",
        "상태": "마감"
    },
    {
        "공모전 제목": "2024 엔지니어링산업 경진대회",
        "분류": "게임/소프트웨어, 기획/아이디어",
        "주최자": "산업통상자원부",
        "남은 기간": "-",
        "접수 기간": "2024-03-04 ~ 2024-04-30",
        "상태": "마감"
    },
    {
        "공모전 제목": "2024년 광진구 빅데이터 분석 공모전",
        "분류": "게임/소프트웨어",
        "주최자": "광진구",
        "남은 기간": "-",
        "접수 기간": "2024-04-01 ~ 2024-05-03",
        "상태": "마감"
    },
    {
        "공모전 제목": "2024 스마일게이트 인디게임 창작 공모전",
        "분류": "게임/소프트웨어",
        "주최자": "스마일게이트 퓨처랩",
        "남은 기간": "-",
        "접수 기간": "2024-02-05 ~ 2024-03-05",
        "상태": "마감"
    },
    {
        "공모전 제목": "인공지능으로 그려보는 해양수산의 미래상 공모전",
        "분류": "게임/소프트웨어, 디자인",
        "주최자": "한국해양수산개발원",
        "남은 기간": "-",
        "접수 기간": "2024-02-05 ~ 2024-02-28",
        "상태": "마감"
    },
    {
        "공모전 제목": "2024 Web3 Ignition Challenge",
        "분류": "게임/소프트웨어",
        "주최자": "주식회사 크립티드",
        "남은 기간": "-",
        "접수 기간": "2024-01-25 ~ 2024-02-13",
        "상태": "마감"
    },
    {
        "공모전 제목": "24년상반기 SW개발공모전(SW개발아이디어 및 결과물)",
        "분류": "게임/소프트웨어",
        "주최자": "한국스마트정보교육원",
        "남은 기간": "-",
        "접수 기간": "2024-01-30 ~ 2024-06-28",
        "상태": "마감"
    },
    {
        "공모전 제목": "제4회 소셜임팩트 디지털아트 경연대회",
        "분류": "게임/소프트웨어, 영상/UCC",
        "주최자": "한국조지메이슨대학교",
        "남은 기간": "-",
        "접수 기간": "2024-02-05 ~ 2024-04-14",
        "상태": "마감"
    },
    {
        "공모전 제목": "제2회 대한민국 NFT 디지털아트대전",
        "분류": "게임/소프트웨어, 대회, 디자인, 만화/캐릭터, 미술, 영상/UCC",
        "주최자": "매일경제신문사",
        "남은 기간": "-",
        "접수 기간": "2024-01-18 ~ 2024-02-29",
        "상태": "마감"
    }
]